shmistogram/__init__.py
shmistogram/names.py
shmistogram/shmistogram.py
shmistogram/utils.py
shmistogram/binners/__init__.py
shmistogram/binners/agglomerate.py
shmistogram/binners/bayesblocks.py
shmistogram/binners/det.py
shmistogram/binners/scalability_testing.py
shmistogram/plot/__init__.py
shmistogram/plot/shmistogrammer.py
shmistogram/simulations/__init__.py
shmistogram/simulations/univariate.py
shmistogram-1.0.0.dist-info/METADATA
shmistogram-1.0.0.dist-info/WHEEL
shmistogram-1.0.0.dist-info/licenses/LICENSE
shmistogram-1.0.0.dist-info/RECORD
