Metadata-Version: 2.4
Name: shmistogram
Version: 1.0.0
Summary: A smarter histogram
Project-URL: Source, https://github.com/zkurtz/shmistogram
License-File: LICENSE
Requires-Python: >=3.10
Requires-Dist: astropy>=3.1.2
Requires-Dist: matplotlib>=3.0.3
Requires-Dist: pandahandler>=0.4.0
Requires-Dist: pandas>=1.5.0
Requires-Dist: scipy>=1.2.1
